{
	"대분류": "교양",
	"중분류": "CJENM",
	"소분류": "썬킴의 한국사 완전정복",
	"ID": "rf_c_331722",
	"S-Code": "ko-KR",
	"T-Code": "fr-FR",
	"S-Length": "51",
	"T-Length": "123",
	"Ratio": "0.414634146",
	"특수표현": "X",
	"원문": "나중에 다시 말씀 드리겠지만, 굉장히 조작의 가능성이 진한 냄새가 나는 그런 사건이었습니다.",
	"MT": "Comme je vous le dirai plus tard, c'était un tel événement qui sentait très inviolable.",
	"1차수정": "Là-dessus, je reviendrai plus tard. En tout cas, c’est une affaire qui sentait fort la manipulation.",
	"2차수정": "Là-dessus, je reviendrai plus tard. En tout cas, c’est une affaire qui a une forte odeur de la possibilité de manipulation.",
	"최종번역문": "Là-dessus, je reviendrai plus tard. En tout cas, c’est une affaire qui a une forte odeur de la possibilité de manipulation."
}