{
	"대분류": "교양",
	"중분류": "CJENM",
	"소분류": "썬킴의 한국사 완전정복",
	"ID": "rf_c_332206",
	"S-Code": "ko-KR",
	"T-Code": "fr-FR",
	"S-Length": "20",
	"T-Length": "84",
	"Ratio": "0.238095238",
	"특수표현": "X",
	"원문": "백골이 진토되어 넋이라도 있고 없고.",
	"MT": "L'épine dorsale est saupoudrée et il n'y a pas d'âme.",
	"1차수정": "Bien que mes os blanchis se transforment en poussière et que mon âme périsse ou non.",
	"2차수정": "N/A",
	"최종번역문": "Bien que mes os blanchis se transforment en poussière et que mon âme périsse ou non."
}