{
	"대분류": "교양",
	"중분류": "CJENM",
	"소분류": "썬킴의 한국사 완전정복",
	"ID": "rf_c_331607",
	"S-Code": "ko-KR",
	"T-Code": "fr-FR",
	"S-Length": "35",
	"T-Length": "88",
	"Ratio": "0.397727273",
	"특수표현": "X",
	"원문": "그리고 또 며칠 동안은 그 용상이라는 왕이 앉는 의자 있잖아요.",
	"MT": "Et pour quelques jours encore, il y a une chaise sur laquelle est assis le roi du dragon.",
	"1차수정": "Et pour quelques jours encore, il y a une chaise sur laquelle est assis le roi du trône.",
	"2차수정": "N/A",
	"최종번역문": "Et pour quelques jours encore, il y a une chaise sur laquelle est assis le roi du trône."
}