{
	"대분류": "교양",
	"중분류": "KBS",
	"소분류": "천상의 컬렉션",
	"ID": "rf_k_346579",
	"S-Code": "ko-KR",
	"T-Code": "fr-FR",
	"S-Length": "39",
	"T-Length": "96",
	"Ratio": "0.40625",
	"특수표현": "X",
	"원문": "세상의 냉대에 지친 최북에게 집은 다다르긴 너무 먼 곳이 아니었을까요?",
	"MT": "Sa maison n'était-elle pas trop loin pour Choe Buk, qui en avait marre de la froideur du monde ?",
	"1차수정": "Sa maison n'était-elle pas trop loin pour Choe Buk, qui en avait assez de la froideur du monde ?",
	"2차수정": "N/A",
	"최종번역문": "Sa maison n'était-elle pas trop loin pour Choe Buk, qui en avait assez de la froideur du monde ?"
}