{
	"대분류": "교양",
	"중분류": "KBS",
	"소분류": "질문하는 기자들 Q",
	"ID": "rf_k_338775",
	"S-Code": "ko-KR",
	"T-Code": "fr-FR",
	"S-Length": "38",
	"T-Length": "105",
	"Ratio": "0.361904762",
	"특수표현": "X",
	"원문": "그런데 요즘도 뉴스를 보는 것이 아이들에게 교육이 되는지는 모르겠다.",
	"MT": "Cependant, je ne sais toujours pas si regarder les informations est éducatif pour les enfants.",
	"1차수정": "Cependant, je ne sais pas si regarder les nouvelles est toujours éducatif pour les enfants.",
	"2차수정": "Cependant, je ne sais pas si regarder les actualités de nos jours est toujours éducatif pour les enfants.",
	"최종번역문": "Cependant, je ne sais pas si regarder les actualités de nos jours est toujours éducatif pour les enfants."
}