{
	"대분류": "교양",
	"중분류": "KBS",
	"소분류": "같이 삽시다",
	"ID": "rf_k_335022",
	"S-Code": "ko-KR",
	"T-Code": "fr-FR",
	"S-Length": "37",
	"T-Length": "87",
	"Ratio": "0.425287356",
	"특수표현": "X",
	"원문": "가을 아침 작은 새들 노랫 소리 들려오면 언제나 그랬듯 잠을 깬다.",
	"MT": "Je me réveille comme je le fais toujours quand j'entends le chant des petits oiseaux le matin d'automne.",
	"1차수정": "Le réveille comme toujours quand il y a du chant des petits oiseaux le matin d'automne.",
	"2차수정": "N/A",
	"최종번역문": "Le réveille comme toujours quand il y a du chant des petits oiseaux le matin d'automne."
}