{
	"대분류": "교양",
	"중분류": "KBS",
	"소분류": "질문하는 기자들 Q",
	"ID": "rf_k_339307",
	"S-Code": "ko-KR",
	"T-Code": "fr-FR",
	"S-Length": "30",
	"T-Length": "102",
	"Ratio": "0.294117647",
	"특수표현": "X",
	"원문": "그리고 공영방송 지배구조 개선 방안을 논의를 했습니다.",
	"MT": "Et ils ont également discuté des moyens d'améliorer la structure de gouvernance de la radiodiffusion publique.",
	"1차수정": "Et ils ont également discuté des moyens d'améliorer la structure de gouvernance de la chaîne publique.",
	"2차수정": "N/A",
	"최종번역문": "Et ils ont également discuté des moyens d'améliorer la structure de gouvernance de la chaîne publique."
}