{
	"대분류": "교양",
	"중분류": "KBS",
	"소분류": "같이 삽시다",
	"ID": "rf_k_345635",
	"S-Code": "ko-KR",
	"T-Code": "fr-FR",
	"S-Length": "22",
	"T-Length": "76",
	"Ratio": "0.289473684",
	"특수표현": "X",
	"원문": "뺄셈을 틀려서 머리가 새하얗게 됐습니다.",
	"MT": "J'ai fait une erreur de soustraction, alors mes cheveux sont devenus blancs.",
	"1차수정": "J'ai fait une erreur de soustraction, alors mes cheveux sont devenus blancs.",
	"2차수정": "N/A",
	"최종번역문": "J'ai fait une erreur de soustraction, alors mes cheveux sont devenus blancs."
}