{
	"대분류": "교양",
	"중분류": "KBS",
	"소분류": "천상의 컬렉션",
	"ID": "rf_k_334734",
	"S-Code": "ko-KR",
	"T-Code": "fr-FR",
	"S-Length": "46",
	"T-Length": "83",
	"Ratio": "0.554216867",
	"특수표현": "X",
	"원문": "580편이 넘는 서사시중에서 서곡에 해당하는 한 부분만 유독 극존칭을 쓰고있습니다.",
	"MT": "Sur plus de 580 poèmes épiques, une seule partie correspondant au prélude a un titre unique.",
	"1차수정": "Sur plus de 580 poèmes épiques, une seule partie est écrite en honorifique extrême.",
	"2차수정": "N/A",
	"최종번역문": "Sur plus de 580 poèmes épiques, une seule partie est écrite en honorifique extrême."
}