{
	"대분류": "교양",
	"중분류": "KBS",
	"소분류": "질문하는 기자들 Q",
	"ID": "rf_k_338368",
	"S-Code": "ko-KR",
	"T-Code": "fr-FR",
	"S-Length": "30",
	"T-Length": "74",
	"Ratio": "0.405405405",
	"특수표현": "X",
	"원문": "그러면서 온라인 기사의 전문성도 떨어지게 되었습니다. ",
	"MT": "Dans le même temps, l'expertise des articles en ligne a également diminué.",
	"1차수정": "Dans le même temps, l'expertise des articles en ligne a également diminué.",
	"2차수정": "N/A",
	"최종번역문": "Dans le même temps, l'expertise des articles en ligne a également diminué."
}