{
	"대분류": "교양",
	"중분류": "KBS",
	"소분류": "천상의컬렉션",
	"ID": "rf_k_339670",
	"S-Code": "ko-KR",
	"T-Code": "fr-FR",
	"S-Length": "30",
	"T-Length": "99",
	"Ratio": "0.303030303",
	"특수표현": "X",
	"원문": "그린 사람의 심리가 굉장히 우울하고 불안하다고 합니다.",
	"MT": "Elle a dit que le peintre est très déprimé et anxieux.",
	"1차수정": "Elle a dit que le peintre est très déprimé et anxieux.",
	"2차수정": "Il a dit que l'état psychologique de la personne qui a dessiné l'image est très déprimé et anxieux.",
	"최종번역문": "Il a dit que l'état psychologique de la personne qui a dessiné l'image est très déprimé et anxieux."
}