{
	"대분류": "교양",
	"중분류": "KBS",
	"소분류": "질문하는 기자들 Q",
	"ID": "rf_k_338152",
	"S-Code": "ko-KR",
	"T-Code": "fr-FR",
	"S-Length": "28",
	"T-Length": "85",
	"Ratio": "0.329411765",
	"특수표현": "X",
	"원문": "그러니까 기사형 광고 자체는 불법이 아닌 거네요? ",
	"MT": "Alors, la publicité de type article n'est-elle pas elle-même illégale ?",
	"1차수정": "Alors, la publicité de type d'article n'est-elle pas elle-même illégale ? ",
	"2차수정": "Alors, la publicité sous forme d'article n'est-elle donc pas illégale en elle même ? ",
	"최종번역문": "Alors, la publicité sous forme d'article n'est-elle donc pas illégale en elle même ? "
}