{
	"대분류": "교양",
	"중분류": "KBS",
	"소분류": "천상의컬렉션",
	"ID": "rf_k_336658",
	"S-Code": "ko-KR",
	"T-Code": "fr-FR",
	"S-Length": "26",
	"T-Length": "69",
	"Ratio": "0.376811594",
	"특수표현": "X",
	"원문": "그 분도 사실 몸이 아파서 온몸이 다 아파서요.",
	"MT": "Cette personne est en fait malade, donc tout son corps lui fait mal.",
	"1차수정": "Cette personne est en fait malade, donc tout son corps lui fait mal. ",
	"2차수정": "N/A",
	"최종번역문": "Cette personne est en fait malade, donc tout son corps lui fait mal. "
}