{
	"대분류": "교양",
	"중분류": "KBS",
	"소분류": "천상의 컬렉션",
	"ID": "rf_k_335473",
	"S-Code": "ko-KR",
	"T-Code": "fr-FR",
	"S-Length": "45",
	"T-Length": "106",
	"Ratio": "0.424528302",
	"특수표현": "X",
	"원문": "겨우 이것을 쌀 두 가마니 값을 주고 샀는가 싶어서 돌을 자세히 들여다 봤습니다.",
	"MT": "J'ai regardé de plus près la pierre pour voir si elle avait été achetée au prix de deux sacs de riz.",
	"1차수정": "J'ai regardé de plus près la pierre pour voir pourquoi elle avait été achetée au prix de deux sacs de riz.",
	"2차수정": "N/A",
	"최종번역문": "J'ai regardé de plus près la pierre pour voir pourquoi elle avait été achetée au prix de deux sacs de riz."
}