{
	"대분류": "교양",
	"중분류": "KBS",
	"소분류": "질문하는 기자들 Q",
	"ID": "rf_k_337547",
	"S-Code": "ko-KR",
	"T-Code": "fr-FR",
	"S-Length": "53",
	"T-Length": "111",
	"Ratio": "0.477477477",
	"특수표현": "X",
	"원문": "그때를 기준으로 했을 때, 더불어 민주당에서 내건 엄청난 공약이 디지털 대전환이라는 공약입니다.",
	"MT": "Sur la base de cette époque, l'énorme promesse du Parti démocrate de Corée est une transformation numérique.",
	"1차수정": "Sur la base de cette époque, l'énorme promesse du Parti démocrate de Corée est une transformation numérique.",
	"2차수정": "En se basant sur ce jour, l'énorme promesse du Parti Démocrate de Corée est la grande transformation numérique.",
	"최종번역문": "En se basant sur ce jour, l'énorme promesse du Parti Démocrate de Corée est la grande transformation numérique."
}