{
	"대분류": "교양",
	"중분류": "KBS",
	"소분류": "질문하는 기자들 Q",
	"ID": "rf_k_338753",
	"S-Code": "ko-KR",
	"T-Code": "fr-FR",
	"S-Length": "38",
	"T-Length": "104",
	"Ratio": "0.365384615",
	"특수표현": "X",
	"원문": "그런데 영상 오른쪽 위를 보면 무속인의 핸드폰 번호가 적혀있습니다. ",
	"MT": "Mais si vous regardez en haut à droite de la vidéo, le numéro de téléphone portable du chaman est écrit.",
	"1차수정": "Mais si vous regardez en haut à droite de la vidéo, le numéro de téléphone portable du chaman est écrit.",
	"2차수정": "N/A",
	"최종번역문": "Mais si vous regardez en haut à droite de la vidéo, le numéro de téléphone portable du chaman est écrit."
}