{
	"대분류": "교양",
	"중분류": "KBS",
	"소분류": "천상의 컬렉션",
	"ID": "rf_k_339124",
	"S-Code": "ko-KR",
	"T-Code": "fr-FR",
	"S-Length": "37",
	"T-Length": "67",
	"Ratio": "0.552238806",
	"특수표현": "X",
	"원문": "그렇게 배들이 많이 침몰했다고 하는데 왜 그 앞을 지나가는 건가요?",
	"MT": "Tant de navires ont coulé, alors pourquoi passent-ils devant eux ?",
	"1차수정": "Tant de navires ont coulé, alors pourquoi passent-ils devant eux ? ",
	"2차수정": "N/A",
	"최종번역문": "Tant de navires ont coulé, alors pourquoi passent-ils devant eux ? "
}