{
	"대분류": "교양",
	"중분류": "KBS",
	"소분류": "천상의컬렉션",
	"ID": "rf_k_337916",
	"S-Code": "ko-KR",
	"T-Code": "fr-FR",
	"S-Length": "36",
	"T-Length": "102",
	"Ratio": "0.352941176",
	"특수표현": "X",
	"원문": "그래서 이러한 주제가 유행되어서 화가들이 많이 찾던 소재였습니다.",
	"MT": "Ces sujets sont donc devenus populaires, et ce sont des sujets que de nombreux artistes recherchaient.",
	"1차수정": "Ces sujets sont donc devenus populaires, et ce sont des sujets que de nombreux artistes recherchaient.",
	"2차수정": "N/A",
	"최종번역문": "Ces sujets sont donc devenus populaires, et ce sont des sujets que de nombreux artistes recherchaient."
}