{
	"대분류": "교양",
	"중분류": "KBS",
	"소분류": "천상의 컬렉션",
	"ID": "rf_k_345675",
	"S-Code": "ko-KR",
	"T-Code": "fr-FR",
	"S-Length": "46",
	"T-Length": "97",
	"Ratio": "0.474226804",
	"특수표현": "X",
	"원문": "사도세자는 대를 이을 아들이 없었던 영조가 42살의 겨우 얻은 귀한 아들이었습니다.",
	"MT": "Le prince héritier Sado était le seul fils précieux du roi Yeongjo, âgé de 42 ans, qui n'avait pas de fils à hériter.",
	"1차수정": "Le prince héritier Sado était le seul fils précieux du roi Yeongjo, qu'il a eu à l'âge de 42 ans.",
	"2차수정": "N/A",
	"최종번역문": "Le prince héritier Sado était le seul fils précieux du roi Yeongjo, qu'il a eu à l'âge de 42 ans."
}