{
	"대분류": "교양",
	"중분류": "MBN",
	"소분류": "생생정보마당",
	"ID": "rf_m_388071",
	"S-Code": "ko-KR",
	"T-Code": "fr-FR",
	"S-Length": "50",
	"T-Length": "127",
	"Ratio": "0.393700787",
	"특수표현": "X",
	"원문": "뭔지 알 것 같아요, 왜냐하면 비타민 c도 피부 건강이랑 관련이 있어서 많이 복용하잖아요.",
	"MT": "Je pense que vous savez ce que c'est, car la vitamine C est également liée à la santé de la peau, donc vous en prenez beaucoup.",
	"1차수정": "Je pense que vous savez ce que c'est, car la vitamine C est également liée à la santé de la peau, donc vous en prenez beaucoup.",
	"2차수정": "N/A",
	"최종번역문": "Je pense que vous savez ce que c'est, car la vitamine C est également liée à la santé de la peau, donc vous en prenez beaucoup."
}