{
	"대분류": "교양",
	"중분류": "MBN",
	"소분류": "생생정보마당",
	"ID": "rf_m_363397",
	"S-Code": "ko-KR",
	"T-Code": "fr-FR",
	"S-Length": "44",
	"T-Length": "121",
	"Ratio": "0.363636364",
	"특수표현": "X",
	"원문": "걸어가기에도 애매하고 뭘 타고 갈수도 없는 곳을 갈 때 공유 킥보드를 이용해요.",
	"MT": "J'utilise une planche partagée lorsque je vais dans des endroits difficiles à marcher et que je ne peux rien monter.",
	"1차수정": "J'utilise une trottinette partagée lorsque je vais dans des endroits difficiles à marcher et que je ne peux rien prendre.",
	"2차수정": "N/A",
	"최종번역문": "J'utilise une trottinette partagée lorsque je vais dans des endroits difficiles à marcher et que je ne peux rien prendre."
}