{
	"대분류": "교양",
	"중분류": "MBN",
	"소분류": "생생정보마당",
	"ID": "rf_m_425378",
	"S-Code": "ko-KR",
	"T-Code": "fr-FR",
	"S-Length": "26",
	"T-Length": "68",
	"Ratio": "0.382352941",
	"특수표현": "X",
	"원문": "전국 과메기의 90% 이상은 포항에서 생산된다.",
	"MT": "Plus de 90% des harengs semi-séchés nationaux sont produits à Pohang.",
	"1차수정": "Plus de 90% des harengs semi-séchés nationaux sont produits à Pohang.",
	"2차수정": "Plus de 90% des hareng semi-séchés nationaux sont produits à Pohang.",
	"최종번역문": "Plus de 90% des hareng semi-séchés nationaux sont produits à Pohang."
}