{
	"대분류": "교양",
	"중분류": "MBN",
	"소분류": "생생정보마당",
	"ID": "rf_m_422590",
	"S-Code": "ko-KR",
	"T-Code": "fr-FR",
	"S-Length": "41",
	"T-Length": "109",
	"Ratio": "0.376146789",
	"특수표현": "X",
	"원문": "저는 그 가게에 가본 적은 없지만 폐업 소식을 들으면서 가슴이 아팠습니다.",
	"MT": "Je n'ai jamais été dans ce magasin, mais j'ai eu le cœur brisé quand j'ai appris la nouvelle de la fermeture.",
	"1차수정": "Je n'ai jamais été dans ce magasin, mais j'ai eu le cœur brisé quand j'ai appris la nouvelle de la fermeture.",
	"2차수정": "N/A",
	"최종번역문": "Je n'ai jamais été dans ce magasin, mais j'ai eu le cœur brisé quand j'ai appris la nouvelle de la fermeture."
}