{
	"대분류": "교양",
	"중분류": "MBN",
	"소분류": "생생정보마당",
	"ID": "rf_m_399604",
	"S-Code": "ko-KR",
	"T-Code": "fr-FR",
	"S-Length": "26",
	"T-Length": "60",
	"Ratio": "0.433333333",
	"특수표현": "X",
	"원문": "아버님 아까 추던 춤은 도대체 무슨 동작인가요?",
	"MT": "Père, quel genre de mouvement avez-vous dansé plus tôt ?",
	"1차수정": "Père, quel genre de mouvement avez-vous dansé plus tôt ?",
	"2차수정": "Monsieur, quel genre de mouvement avez-vous dansé plus tôt ?",
	"최종번역문": "Monsieur, quel genre de mouvement avez-vous dansé plus tôt ?"
}