{
	"대분류": "교양",
	"중분류": "MBN",
	"소분류": "생생정보마당",
	"ID": "rf_m_393987",
	"S-Code": "ko-KR",
	"T-Code": "fr-FR",
	"S-Length": "28",
	"T-Length": "83",
	"Ratio": "0.337349398",
	"특수표현": "X",
	"원문": "새해에는 맛있는 음식 드시면서 다이어트 성공하세요.",
	"MT": "Dans la nouvelle année, tout en mangeant des plats délicieux, réussissez un régime.",
	"1차수정": "Dans la nouvelle année, tout en mangeant des plats délicieux, réussissez un régime.",
	"2차수정": "N/A",
	"최종번역문": "Dans la nouvelle année, tout en mangeant des plats délicieux, réussissez un régime."
}