{
	"대분류": "교양",
	"중분류": "MBN",
	"소분류": "생생정보마당",
	"ID": "rf_m_432474",
	"S-Code": "ko-KR",
	"T-Code": "fr-FR",
	"S-Length": "24",
	"T-Length": "81",
	"Ratio": "0.296296296",
	"특수표현": "X",
	"원문": "천연 미네랄이 가득한 보령 머드 파우더예요.",
	"MT": "Poudre de boue Boryeong pleine de minéraux naturels.",
	"1차수정": "C'est de la poudre de boue de Boryeong, pleine de minéraux naturels.",
	"2차수정": "C'est de la poudre de l'argile de Boryeong, elle est pleine de minéraux naturels.",
	"최종번역문": "C'est de la poudre de l'argile de Boryeong, elle est pleine de minéraux naturels."
}