{
	"대분류": "교양",
	"중분류": "MBN",
	"소분류": "생생정보마당",
	"ID": "rf_m_375956",
	"S-Code": "ko-KR",
	"T-Code": "fr-FR",
	"S-Length": "34",
	"T-Length": "87",
	"Ratio": "0.390804598",
	"특수표현": "X",
	"원문": "나는 아기를 낳은 후에 살이 처지고 몸이 무거워졌음을 실감했다",
	"MT": "Après avoir accouché, j'ai réalisé que j'avais perdu du poids et pris du poids.",
	"1차수정": "Après avoir donné naissance au bébé, j'ai réalisé que j'étais devenue grosse et lourde.",
	"2차수정": "N/A",
	"최종번역문": "Après avoir donné naissance au bébé, j'ai réalisé que j'étais devenue grosse et lourde."
}