{
	"대분류": "교양",
	"중분류": "MBN",
	"소분류": "생생정보마당",
	"ID": "rf_m_409801",
	"S-Code": "ko-KR",
	"T-Code": "fr-FR",
	"S-Length": "21",
	"T-Length": "79",
	"Ratio": "0.265822785",
	"특수표현": "X",
	"원문": "요즘 들어 온몸이 쑤시고 손발이 차요.",
	"MT": "Ces jours-ci, tout mon corps me fait mal et j'ai froid aux mains et aux pieds.",
	"1차수정": "Ces jours-ci, tout mon corps me fait mal et j'ai froid aux mains et aux pieds. ",
	"2차수정": "N/A",
	"최종번역문": "Ces jours-ci, tout mon corps me fait mal et j'ai froid aux mains et aux pieds. "
}