{
	"대분류": "교양",
	"중분류": "MBN",
	"소분류": "생생정보마당",
	"ID": "rf_m_360825",
	"S-Code": "ko-KR",
	"T-Code": "fr-FR",
	"S-Length": "46",
	"T-Length": "101",
	"Ratio": "0.455445545",
	"특수표현": "X",
	"원문": "3살 때 다쳐서 상해를 입어서 오른쪽 다리가 왼쪽 다리에 비해서 13cm가 짧아요.",
	"MT": "J'ai été blessé quand j'avais 3 ans, donc ma jambe droite est 13 cm plus courte que ma jambe gauche.",
	"1차수정": "J'ai été blessé quand j'avais 3 ans, donc ma jambe droite est 13 cm plus courte que ma jambe gauche. ",
	"2차수정": "N/A",
	"최종번역문": "J'ai été blessé quand j'avais 3 ans, donc ma jambe droite est 13 cm plus courte que ma jambe gauche. "
}