{
	"대분류": "교양",
	"중분류": "MBN",
	"소분류": "생생정보마당",
	"ID": "rf_m_384196",
	"S-Code": "ko-KR",
	"T-Code": "fr-FR",
	"S-Length": "40",
	"T-Length": "101",
	"Ratio": "0.396039604",
	"특수표현": "X",
	"원문": "로봇이 아닌 이상 모든 사람의 다리 길이에 차이가 조금씩 날 것 같아요.",
	"MT": "À moins que vous ne soyez un robot, je pense que la longueur des jambes de chacun sera légèrement différente.",
	"1차수정": "Sauf si vous êtes un robot, je pense que la longueur des jambes de chacun sera légèrement différente.",
	"2차수정": "N/A",
	"최종번역문": "Sauf si vous êtes un robot, je pense que la longueur des jambes de chacun sera légèrement différente."
}