{
	"대분류": "교양",
	"중분류": "MBN",
	"소분류": "생생정보마당",
	"ID": "rf_m_439888",
	"S-Code": "ko-KR",
	"T-Code": "fr-FR",
	"S-Length": "35",
	"T-Length": "83",
	"Ratio": "0.421686747",
	"특수표현": "X",
	"원문": "힘든줄도 모르고 재미가 있는지 없는지도 모르고 그냥 살아냈어요.",
	"MT": "Je ne savais pas que c'était dur, je ne savais pas si c'était amusant ou pas, et je l'ai juste vécu.",
	"1차수정": "J'ai juste vécu sans vraiement savoir si c'était dur, et si c'était amusant ou pas.",
	"2차수정": "N/A",
	"최종번역문": "J'ai juste vécu sans vraiement savoir si c'était dur, et si c'était amusant ou pas."
}