{
	"대분류": "교양",
	"중분류": "MBN",
	"소분류": "생생정보마당",
	"ID": "rf_m_429401",
	"S-Code": "ko-KR",
	"T-Code": "fr-FR",
	"S-Length": "21",
	"T-Length": "91",
	"Ratio": "0.230769231",
	"특수표현": "X",
	"원문": "지글지글 익혀서 한입 먹으면 맛있겠죠?",
	"MT": "Ce sera bien si vous le faites grésiller et que vous en prenez une bouchée, n'est-ce pas ?",
	"1차수정": "Ce sera bien si vous le faites grésiller et que vous en prenez une bouchée, n'est-ce pas ? ",
	"2차수정": "N/A",
	"최종번역문": "Ce sera bien si vous le faites grésiller et que vous en prenez une bouchée, n'est-ce pas ? "
}