{
	"대분류": "교양",
	"중분류": "MBN",
	"소분류": "생생정보마당",
	"ID": "rf_m_374844",
	"S-Code": "ko-KR",
	"T-Code": "fr-FR",
	"S-Length": "38",
	"T-Length": "82",
	"Ratio": "0.463414634",
	"특수표현": "X",
	"원문": "기침이 과격하게 나올 때도 있지만 성호 씨는 대수롭지 않게 넘깁니다.",
	"MT": "Il y a des moments où une toux sort violemment, mais Seong-ho la passe légèrement.",
	"1차수정": "Il y a des moments où une toux sort violemment, mais Seong-ho la passe légèrement.",
	"2차수정": "N/A",
	"최종번역문": "Il y a des moments où une toux sort violemment, mais Seong-ho la passe légèrement."
}