{
	"대분류": "교양",
	"중분류": "MBN",
	"소분류": "생생정보마당",
	"ID": "rf_m_379428",
	"S-Code": "ko-KR",
	"T-Code": "fr-FR",
	"S-Length": "53",
	"T-Length": "132",
	"Ratio": "0.401515152",
	"특수표현": "X",
	"원문": "눈 건강을 지키기 위해서는 시력의 90%를 담당하고 있는 황반의 건강을 유지하는 게 중요한데요.",
	"MT": "Pour garder les yeux en bonne santé, il est important de maintenir la santé de la macula, qui est responsable de 90 % de la vision.",
	"1차수정": "Pour garder les yeux en bonne santé, il est important de maintenir la santé de la macula, qui est responsable de 90 % de la vision. ",
	"2차수정": "N/A",
	"최종번역문": "Pour garder les yeux en bonne santé, il est important de maintenir la santé de la macula, qui est responsable de 90 % de la vision. "
}