{
	"대분류": "교양",
	"중분류": "MBN",
	"소분류": "생생정보마당",
	"ID": "rf_m_393096",
	"S-Code": "ko-KR",
	"T-Code": "fr-FR",
	"S-Length": "35",
	"T-Length": "78",
	"Ratio": "0.448717949",
	"특수표현": "X",
	"원문": "사장님, 제가 이 집 커피가 그렇게 맛있다고 해서 찾아왔거든요.",
	"MT": "Patron, je suis venu ici parce que j'ai entendu dire que ce café était si bon.",
	"1차수정": "Patron, je suis venu ici parce que j'ai entendu dire que ce café était si bon.",
	"2차수정": "N/A",
	"최종번역문": "Patron, je suis venu ici parce que j'ai entendu dire que ce café était si bon."
}