{
	"대분류": "교양",
	"중분류": "MBN",
	"소분류": "생생정보마당",
	"ID": "rf_m_385957",
	"S-Code": "ko-KR",
	"T-Code": "fr-FR",
	"S-Length": "31",
	"T-Length": "91",
	"Ratio": "0.340659341",
	"특수표현": "X",
	"원문": "먹고 싶으시겠지만 오늘도 음식은 제 입으로만 들어갑니다.",
	"MT": "Vous voudrez peut-être en manger, mais aujourd'hui, la nourriture ne va que dans ma bouche.",
	"1차수정": "Vous voudrez peut-être en manger, mais aujourd'hui, la nourriture ne va que dans ma bouche.",
	"2차수정": "N/A",
	"최종번역문": "Vous voudrez peut-être en manger, mais aujourd'hui, la nourriture ne va que dans ma bouche."
}