{
	"대분류": "교양",
	"중분류": "MBN",
	"소분류": "생생정보마당",
	"ID": "rf_m_377576",
	"S-Code": "ko-KR",
	"T-Code": "fr-FR",
	"S-Length": "32",
	"T-Length": "86",
	"Ratio": "0.372093023",
	"특수표현": "X",
	"원문": "내일 날씨가 좋으면 바다에 가서 멍게를 따서 보여드릴게요.",
	"MT": "S'il fait beau demain, j'irai à la mer cueillir des oursins et vous les montrer.",
	"1차수정": "S'il fait beau demain, j'irai à la mer cueillir des figues de mer et vous les montrer.",
	"2차수정": "N/A",
	"최종번역문": "S'il fait beau demain, j'irai à la mer cueillir des figues de mer et vous les montrer."
}