{
	"대분류": "교양",
	"중분류": "MBN",
	"소분류": "생생정보마당",
	"ID": "rf_m_409149",
	"S-Code": "ko-KR",
	"T-Code": "fr-FR",
	"S-Length": "33",
	"T-Length": "69",
	"Ratio": "0.47826087",
	"특수표현": "X",
	"원문": "와사비가 굉장히 많이 들어가 있어서 조금 힘들 수 있어요. ",
	"MT": "Cela peut être un peu difficile car il y a beaucoup de wasabi dedans.",
	"1차수정": "Cela peut être un peu difficile car il y a beaucoup de wasabi dedans.",
	"2차수정": "N/A",
	"최종번역문": "Cela peut être un peu difficile car il y a beaucoup de wasabi dedans."
}